[
  {
    "_id": 1,
    "producto_id": 3,
    "cantidad": 2,
    "total": 160.0,
    "fecha": "2023-10-25"
  },
  {
    "_id": 2,
    "producto_id": 5,
    "cantidad": 1,
    "total": 65.25,
    "fecha": "2023-10-26"
  },
  {
    "_id": 3,
    "producto_id": 7,
    "cantidad": 3,
    "total": 75.0,
    "fecha": "2023-10-27"
  },
  {
    "_id": 4,
    "producto_id": 5,
    "cantidad": 1,
    "total": 45.5,
    "fecha": "2023-10-28"
  },
  {
    "_id": 5,
    "producto_id": 10,
    "cantidad": 2,
    "total": 60.0,
    "fecha": "2023-10-29"
  },
  {
    "_id": 6,
    "producto_id": 3,
    "cantidad": 1,
    "total": 95.99,
    "fecha": "2023-10-30"
  },
  {
    "_id": 7,
    "producto_id": 1,
    "cantidad": 4,
    "total": 83.96,
    "fecha": "2023-10-31"
  },
  {
    "_id": 8,
    "producto_id": 8,
    "cantidad": 1,
    "total": 50.49,
    "fecha": "2023-11-01"
  },
  {
    "_id": 9,
    "producto_id": 4,
    "cantidad": 2,
    "total": 241.5,
    "fecha": "2023-11-02"
  },
  {
    "_id": 10,
    "producto_id": 4,
    "cantidad": 3,
    "total": 47.25,
    "fecha": "2023-11-02"
  }
]

